django_scaffold_tools-0.0.68.dist-info/licenses/LICENSE
scaffold/__init__.py
scaffold/version.py
scaffold/apps/__init__.py
scaffold/apps/config/__init__.py
scaffold/apps/config/admin.py
scaffold/apps/config/apps.py
scaffold/apps/config/models.py
scaffold/apps/config/serializers.py
scaffold/apps/config/tests.py
scaffold/apps/config/views.py
scaffold/apps/config/migrations/0001_initial.py
scaffold/apps/config/migrations/__init__.py
scaffold/apps/media/__init__.py
scaffold/apps/media/admin.py
scaffold/apps/media/apps.py
scaffold/apps/media/models.py
scaffold/apps/media/serializers.py
scaffold/apps/media/tests.py
scaffold/apps/media/views.py
scaffold/apps/media/migrations/0001_initial.py
scaffold/apps/media/migrations/0002_auto_20250321_1110.py
scaffold/apps/media/migrations/__init__.py
scaffold/exceptions/__init__.py
scaffold/exceptions/exceptions.py
scaffold/exceptions/middleware.py
scaffold/exceptions/utils.py
scaffold/middlewares/__init__.py
scaffold/middlewares/middleware.py
scaffold/models/__init__.py
scaffold/models/abstract/__init__.py
scaffold/models/abstract/member.py
scaffold/models/abstract/meta.py
scaffold/models/entity/__init__.py
scaffold/modules/__init__.py
scaffold/modules/apps.py
scaffold/modules/fullclean.py
scaffold/restframework/__init__.py
scaffold/restframework/apps.py
scaffold/restframework/authentication.py
scaffold/restframework/filters.py
scaffold/restframework/pagination.py
scaffold/restframework/permissions.py
scaffold/restframework/serializers.py
scaffold/restframework/utils.py
scaffold/settings/__init__.py
scaffold/utils/__init__.py
scaffold/utils/apps.py
scaffold/utils/db_router.py
scaffold/utils/http.py
scaffold/utils/vcode/__init__.py
scaffold/utils/vcode/const.py
scaffold/utils/vcode/functions.py
scaffold/utils/vcode/setup_send.py
django_scaffold_tools-0.0.68.dist-info/METADATA
django_scaffold_tools-0.0.68.dist-info/WHEEL
django_scaffold_tools-0.0.68.dist-info/top_level.txt
django_scaffold_tools-0.0.68.dist-info/RECORD
