Metadata-Version: 2.4
Name: django-scaffold-tools
Version: 0.0.68
Summary: A reusable django-app set for a DRF django project, starting support from django 3.0.
Home-page: https://github.com/easecloud/django-scaffold-tools
Author: Alfred Huang
Author-email: 57082212@qq.com
License: Apache License Version 2.0
Classifier: Development Status :: 1 - Planning
Classifier: Environment :: Web Environment
Classifier: Framework :: Django
Classifier: Framework :: Django :: 3.0
Classifier: Intended Audience :: Developers
Classifier: License :: OSI Approved :: Apache Software License
Classifier: Operating System :: OS Independent
Classifier: Programming Language :: Python
Classifier: Programming Language :: Python :: 3
Classifier: Programming Language :: Python :: 3 :: Only
Classifier: Programming Language :: Python :: 3.6
Classifier: Programming Language :: Python :: 3.7
Classifier: Programming Language :: Python :: 3.8
Classifier: Topic :: Internet :: WWW/HTTP
Classifier: Topic :: Internet :: WWW/HTTP :: Dynamic Content
License-File: LICENSE
Requires-Dist: django<4,>=3
Requires-Dist: django-cors-headers
Requires-Dist: django-cron
Requires-Dist: django-filter
Requires-Dist: django-fullclean
Requires-Dist: django-uuslug
Requires-Dist: djangorestframework<4,>=3
Requires-Dist: djangorestframework-queryfields
Requires-Dist: djangorestframework-yaml
Requires-Dist: pillow
Requires-Dist: requests
Dynamic: license-file
Dynamic: requires-dist
